[
  {
    "id": 1,
    "title": "Аналитик данных",
    "description": "Работа с большими массивами данных, поиск закономерностей",
    "interests": ["Данные", "Логика", "IT"],
    "level": "Средний",
    "link": "https://example.com/data-analyst"
  },
  {
    "id": 2,
    "title": "UX/UI Дизайнер",
    "description": "Создает удобные и красивые интерфейсы",
    "interests": ["Творчество", "Люди", "Технологии"],
    "level": "Средний",
    "link": "https://example.com/ux-ui"
  },
  {
    "id": 3,
    "title": "SMM-менеджер",
    "description": "Продвигает бренды в соцсетях и общается с аудиторией",
    "interests": ["Маркетинг", "Общение", "Творчество"],
    "level": "Легкий старт",
    "link": "https://example.com/smm"
  }
]
